datamax_printer/__init__.py
datamax_printer/datamax_printer.py
datamax_printer-0.1.1.dist-info/LICENSE.md
datamax_printer-0.1.1.dist-info/METADATA
datamax_printer-0.1.1.dist-info/WHEEL
datamax_printer-0.1.1.dist-info/top_level.txt
datamax_printer-0.1.1.dist-info/RECORD
