Metadata-Version: 2.1
Name: datamax-printer
Version: 0.1.1
Summary: Controll a datamax o'neil labelprinter using DPL
Home-page: https://github.com/inNETMonitoring/datamax-python-adapter
Author: Michael Blättler
Author-email: michael.blaettler@innetag.ch
License: UNKNOWN
Platform: UNKNOWN
Classifier: Development Status :: 4 - Beta
Classifier: Intended Audience :: Developers
Classifier: Intended Audience :: Manufacturing
Classifier: Programming Language :: Python :: 3.6
Classifier: License :: OSI Approved :: MIT License
Classifier: Operating System :: OS Independent
Classifier: Topic :: Software Development :: Libraries
